ScikitLearnMiji/README.md
ScikitLearnMiji/__init__.py
ScikitLearnMiji/__main__.py
ScikitLearnMiji/file.epub
ScikitLearnMiji/index.html
ScikitLearnMiji/css/__init__.py
ScikitLearnMiji/css/annotations.css
ScikitLearnMiji/css/main.css
ScikitLearnMiji/css/normalize.css
ScikitLearnMiji/css/popup.css
ScikitLearnMiji/font/__init__.py
ScikitLearnMiji/font/fontello.eot
ScikitLearnMiji/font/fontello.svg
ScikitLearnMiji/font/fontello.ttf
ScikitLearnMiji/font/fontello.woff
ScikitLearnMiji/img/__init__.py
ScikitLearnMiji/img/annotator-glyph-sprite.png
ScikitLearnMiji/img/annotator-icon-sprite.png
ScikitLearnMiji/img/apple-touch-icon.png
ScikitLearnMiji/img/cancelfullscreen.png
ScikitLearnMiji/img/close.png
ScikitLearnMiji/img/fullscreen.png
ScikitLearnMiji/img/loader.gif
ScikitLearnMiji/img/menu-icon.png
ScikitLearnMiji/img/save.png
ScikitLearnMiji/img/saved.png
ScikitLearnMiji/img/settings-s.png
ScikitLearnMiji/img/settings.png
ScikitLearnMiji/img/star.png
ScikitLearnMiji/js/__init__.py
ScikitLearnMiji/js/epub.js
ScikitLearnMiji/js/epub.min.js
ScikitLearnMiji/js/epub.min.map
ScikitLearnMiji/js/hooks.min.js
ScikitLearnMiji/js/hooks.min.map
ScikitLearnMiji/js/reader.js
ScikitLearnMiji/js/reader.js.map
ScikitLearnMiji/js/reader.min.js
ScikitLearnMiji/js/reader.min.map
ScikitLearnMiji/js/hooks/__init__.py
ScikitLearnMiji/js/hooks/extensions/__init__.py
ScikitLearnMiji/js/hooks/extensions/highlight.js
ScikitLearnMiji/js/libs/__init__.py
ScikitLearnMiji/js/libs/jquery.min.js
ScikitLearnMiji/js/libs/localforage.min.js
ScikitLearnMiji/js/libs/screenfull.js
ScikitLearnMiji/js/libs/screenfull.min.js
ScikitLearnMiji/js/libs/zip.min.js
ScikitLearnMiji/js/plugins/__init__.py
ScikitLearnMiji/js/plugins/hypothesis.js
ScikitLearnMiji/js/plugins/search.js
scikit_learn_miji-2024.3.2.0.dist-info/METADATA
scikit_learn_miji-2024.3.2.0.dist-info/WHEEL
scikit_learn_miji-2024.3.2.0.dist-info/entry_points.txt
scikit_learn_miji-2024.3.2.0.dist-info/top_level.txt
scikit_learn_miji-2024.3.2.0.dist-info/RECORD
